Metadata-Version: 2.1
Name: processrunner-kitchenpatch
Version: 1.0.7
Summary: Patched getwriter method for Kitchen package
Author-email: Andy Robb <andy@andyrobb.com>
License: 		    GNU GENERAL PUBLIC LICENSE
